aws_cdk_serverbluegreendeploymentgroup/__init__.py
aws_cdk_serverbluegreendeploymentgroup/py.typed
aws_cdk_serverbluegreendeploymentgroup/_jsii/__init__.py
aws_cdk_serverbluegreendeploymentgroup/_jsii/aws-cdk-serverbluegreendeploymentgroup@1.0.3.jsii.tgz
aws_cdk_serverbluegreendeploymentgroup-1.0.3.dist-info/LICENSE
aws_cdk_serverbluegreendeploymentgroup-1.0.3.dist-info/METADATA
aws_cdk_serverbluegreendeploymentgroup-1.0.3.dist-info/WHEEL
aws_cdk_serverbluegreendeploymentgroup-1.0.3.dist-info/top_level.txt
aws_cdk_serverbluegreendeploymentgroup-1.0.3.dist-info/RECORD
