Metadata-Version: 2.1
Name: aws-cdk-serverbluegreendeploymentgroup
Version: 1.0.3
Summary: @otocolobus/aws-cdk-serverbluegreendeploymentgroup
Home-page: https://github.com/otocolobus-com/aws-cdk-serverbluegreendeploymentgroup.git
Author: Otocolobus Sp. z o.o.<start@otocolobus.com>
License: MIT
Project-URL: Source, https://github.com/otocolobus-com/aws-cdk-serverbluegreendeploymentgroup.git
Classifier: Intended Audience :: Developers
Classifier: Operating System :: OS Independent
Classifier: Programming Language :: JavaScript
Classifier: Programming Language :: Python :: 3 :: Only
Classifier: Programming Language :: Python :: 3.8
Classifier: Programming Language :: Python :: 3.9
Classifier: Programming Language :: Python :: 3.10
Classifier: Programming Language :: Python :: 3.11
Classifier: Typing :: Typed
Classifier: Development Status :: 5 - Production/Stable
Classifier: License :: OSI Approved
Requires-Python: ~=3.8
License-File: LICENSE
Requires-Dist: aws-cdk-lib<3.0.0,>=2.154.1
Requires-Dist: constructs<11.0.0,>=10.0.5
Requires-Dist: jsii<2.0.0,>=1.101.0
Requires-Dist: publication>=0.0.3
Requires-Dist: typeguard~=2.13.3
